{
  "locations": {
    "classroom": {
      "name": "Mathematics Classroom",
      "description": "A bright room with whiteboards, desks, and chairs where math lessons take place",
      "function": "Teaching and learning activities"
    },
    "library": {
      "name": "School Library",
      "description": "A quiet place filled with books, computers, and study tables",
      "function": "Individual study and research"
    },
    "cafeteria": {
      "name": "School Cafeteria",
      "description": "A large room where students and staff eat meals and socialize",
      "function": "Eating and social interaction"
    },
    "playground": {
      "name": "School Playground",
      "description": "An outdoor area with sports equipment and open space",
      "function": "Physical activities and recreation"
    },
    "office": {
      "name": "Teacher's Office",
      "description": "A private workspace for teachers to prepare lessons and meet students",
      "function": "Office work and consultations"
    }
  },
  "initial_positions": {
    "teacher": "office",
    "student1": "classroom",
    "student2": "classroom", 
    "student3": "classroom",
    "student4": "classroom"
  }
}